rv_strategy_mb/__init__.py
rv_strategy_mb/backtest.py
rv_strategy_mb/blockchain/trading_signals.pkl
rv_strategy_mb/executor.py
rv_strategy_mb/signal_generator.py
rv_strategy_mb-0.5.1.dist-info/LICENSE
rv_strategy_mb-0.5.1.dist-info/METADATA
rv_strategy_mb-0.5.1.dist-info/WHEEL
rv_strategy_mb-0.5.1.dist-info/RECORD
