Metadata-Version: 2.1
Name: rv-strategy-mb
Version: 0.5.1
Summary: Python Trading Strategy
License: MIT
Author: Marion BIGOTTE
Requires-Python: >=3.11,<4.0
Classifier: License :: OSI Approved :: MIT License
Classifier: Programming Language :: Python :: 3
Classifier: Programming Language :: Python :: 3.11
Requires-Dist: colorama (>=0.4.6,<0.5.0)
Requires-Dist: matplotlib (>=3.10.0,<4.0.0)
Requires-Dist: numba (>=0.60.0,<0.61.0)
Requires-Dist: pandas (>=2.2.3,<3.0.0)
Requires-Dist: sec-cik-mapper (>=2.1.0,<3.0.0)
Requires-Dist: yfinance (>=0.2.51,<0.3.0)
